README.rst
setup.py
bin/churchdir-quickstart
churchdir/__init__.py
churchdir/quickstart.py
churchdir.egg-info/PKG-INFO
churchdir.egg-info/SOURCES.txt
churchdir.egg-info/dependency_links.txt
churchdir.egg-info/requires.txt
churchdir.egg-info/top_level.txt