Metadata-Version: 1.1
Name: churchdir
Version: 0.3
Summary: Convert an address book from csv format to a web page.
Home-page: http://c-c-church.net/directory-software/
Author: Ken Carlton
Author-email: kcarlton@c-c-church.net
License: BSD
Keywords: church directory address book csv
Platform: any
Classifier: Development Status :: 3 - Alpha
Classifier: Programming Language :: Python
Classifier: Environment :: Console
Classifier: Environment :: Web Environment
Classifier: Topic :: Communications :: Email :: Address Book
Classifier: Topic :: Religion
Classifier: Topic :: Utilities
Classifier: License :: OSI Approved :: BSD License
